concat_all/__init__.py
concat_all/__main__.py
concat_all/concat_all.py
concat_all-0.3.0.dist-info/licenses/LICENSE
concat_all-0.3.0.dist-info/METADATA
concat_all-0.3.0.dist-info/WHEEL
concat_all-0.3.0.dist-info/entry_points.txt
concat_all-0.3.0.dist-info/top_level.txt
concat_all-0.3.0.dist-info/RECORD
