Metadata-Version: 2.4
Name: concat-all
Version: 0.3.0
Summary: A simple CLI tool to recursively concatenate all files of a certain extension in a directory into a single file
License: MIT
Requires-Python: >=3.9
License-File: LICENSE
Requires-Dist: pathspec>=0.12
Dynamic: license-file
